{
  "id": "0b0847c2e3ab",
  "title": "Day 1174",
  "createdAt": "2025-06-09 02:51:20",
  "tags": [
    "no",
    "money",
    "changers",
    "one-fair-set-of-rules",
    "bitcoin"
  ],
  "url": "https://chepenikconor.medium.com/day-1174-0b0847c2e3ab",
  "content": "# Day 1174\n\nOne thing about me. I will spread Bitcoin propoganda shameslessly. I will help orange pill others because I feel it is a moral imperative. It makes the world a better place.\n\n![Shiny Swan B](https://miro.medium.com/1*qrq8J-uEce3AyH74ow94TA.png)\n\n![[https://x.com/ConorChepenik/status/1931898533143290032](https://x.com/ConorChepenik/status/1931898533143290032)](https://miro.medium.com/1*DC-BurBbN1AiN8Rs5gqm2w.png)\n\n![Bitcoin cat](https://miro.medium.com/1*pdKjA39LsekGfwHUktufWg.png)\n\nAnd the best part? AI makes it so easy to do so.\n\n6/8/25\n\nConor Jay Chepenik",
  "wordCount": 49,
  "readingTime": 0.7349056603773585,
  "claps": 0,
  "voters": 0
}