{
  "id": "f2cbd4a213a9",
  "title": "Day 1006",
  "createdAt": "2024-12-22 20:06:07",
  "tags": [
    "simple",
    "advice",
    "yet",
    "often",
    "forgotten"
  ],
  "url": "https://chepenikconor.medium.com/day-1006-f2cbd4a213a9",
  "content": "# Day 1006\n\nIt is hard to overstate how crucial exercise is for happiness. Whenever I feel down I go for a run, hit the gym, or shoot some hoops. It does not matter what type of exercise you do, just that you exercise. Without fail, when I exercise it makes me feel better. Our bodies are designed to move. If we don't move then we become depressed. Simple as.\n\nSo exercise more. Your body needs it to be at peace.\n\n12/22/24\n\nConor Jay Chepenik",
  "wordCount": 84,
  "readingTime": 0.3169811320754717,
  "claps": 0,
  "voters": 0
}